nam/__init__.py
nam/__main__.py
nam/config.txt
nam/download.py
nam/upload.py
nexus_artifact_manager-1.1.9.dist-info/METADATA
nexus_artifact_manager-1.1.9.dist-info/WHEEL
nexus_artifact_manager-1.1.9.dist-info/entry_points.txt
nexus_artifact_manager-1.1.9.dist-info/top_level.txt
nexus_artifact_manager-1.1.9.dist-info/RECORD
