Metadata-Version: 2.1
Name: nexus-artifact-manager
Version: 1.1.9
Summary: Upload and Download artifact from Nexus v3+ repository
Home-page: https://github.com/stewiejnr/nexus-artifact-manager
Author: Stewartium
Author-email: stewartium1@gmail.com
License: MIT
Platform: UNKNOWN
Classifier: License :: OSI Approved :: MIT License
Classifier: Programming Language :: Python :: 3
Classifier: Programming Language :: Python :: 3.7
Requires-Dist: requests
Requires-Dist: urllib3
